[{"name":"Ria PERCIVAL","captain":false,"shirt_number":2,"position":0,"Favorite":false,"PicturePath":null},{"name":"C.J. BOTT","captain":false,"shirt_number":4,"position":0,"Favorite":false,"PicturePath":null},{"name":"Rebekah STOTT","captain":false,"shirt_number":6,"position":0,"Favorite":false,"PicturePath":null},{"name":"Ali RILEY","captain":true,"shirt_number":7,"position":0,"Favorite":false,"PicturePath":null},{"name":"Abby ERCEG","captain":false,"shirt_number":8,"position":0,"Favorite":false,"PicturePath":null},{"name":"Sarah GREGORIUS","captain":false,"shirt_number":11,"position":1,"Favorite":false,"PicturePath":null},{"name":"Betsy HASSETT","captain":false,"shirt_number":12,"position":3,"Favorite":false,"PicturePath":null},{"name":"Rosie WHITE","captain":false,"shirt_number":13,"position":1,"Favorite":false,"PicturePath":null},{"name":"Katie BOWEN","captain":false,"shirt_number":14,"position":3,"Favorite":false,"PicturePath":null},{"name":"Olivia CHANCE","captain":false,"shirt_number":22,"position":3,"Favorite":false,"PicturePath":null},{"name":"Anna GREEN","captain":false,"shirt_number":3,"position":0,"Favorite":false,"PicturePath":null},{"name":"Nicole STRATFORD","captain":false,"shirt_number":5,"position":0,"Favorite":false,"PicturePath":null},{"name":"Emma KETE","captain":false,"shirt_number":9,"position":1,"Favorite":false,"PicturePath":null},{"name":"Annalie LONGO","captain":false,"shirt_number":10,"position":3,"Favorite":false,"PicturePath":null},{"name":"Sarah MORTON","captain":false,"shirt_number":15,"position":0,"Favorite":false,"PicturePath":null},{"name":"Katie DUNCAN","captain":false,"shirt_number":16,"position":3,"Favorite":false,"PicturePath":null},{"name":"Hannah WILKINSON","captain":false,"shirt_number":17,"position":1,"Favorite":false,"PicturePath":null},{"name":"Steph SKILTON","captain":false,"shirt_number":18,"position":0,"Favorite":false,"PicturePath":null},{"name":"Paige SATCHELL","captain":false,"shirt_number":19,"position":1,"Favorite":false,"PicturePath":null},{"name":"Daisy CLEVERLEY","captain":false,"shirt_number":20,"position":3,"Favorite":false,"PicturePath":null},{"name":"Victoria ESSON","captain":false,"shirt_number":21,"position":2,"Favorite":false,"PicturePath":null},{"name":"Nadia OLLA","captain":false,"shirt_number":23,"position":2,"Favorite":false,"PicturePath":null},{"name":"Erin NAYLER","captain":false,"shirt_number":1,"position":2,"Favorite":true,"PicturePath":"C:\\Users\\jkustan\\Pictures\\_1430201.jpg"},{"name":"Ria PERCIVAL","captain":false,"shirt_number":2,"position":0,"Favorite":false,"PicturePath":null},{"name":"C.J. BOTT","captain":false,"shirt_number":4,"position":0,"Favorite":false,"PicturePath":null},{"name":"Rebekah STOTT","captain":false,"shirt_number":6,"position":0,"Favorite":false,"PicturePath":null},{"name":"Ali RILEY","captain":true,"shirt_number":7,"position":0,"Favorite":false,"PicturePath":null},{"name":"Abby ERCEG","captain":false,"shirt_number":8,"position":0,"Favorite":false,"PicturePath":null},{"name":"Sarah GREGORIUS","captain":false,"shirt_number":11,"position":1,"Favorite":false,"PicturePath":null},{"name":"Betsy HASSETT","captain":false,"shirt_number":12,"position":3,"Favorite":false,"PicturePath":null},{"name":"Rosie WHITE","captain":false,"shirt_number":13,"position":1,"Favorite":false,"PicturePath":null},{"name":"Katie BOWEN","captain":false,"shirt_number":14,"position":3,"Favorite":false,"PicturePath":null},{"name":"Olivia CHANCE","captain":false,"shirt_number":22,"position":3,"Favorite":false,"PicturePath":null},{"name":"Anna GREEN","captain":false,"shirt_number":3,"position":0,"Favorite":false,"PicturePath":null},{"name":"Nicole STRATFORD","captain":false,"shirt_number":5,"position":0,"Favorite":false,"PicturePath":null},{"name":"Emma KETE","captain":false,"shirt_number":9,"position":1,"Favorite":false,"PicturePath":null},{"name":"Annalie LONGO","captain":false,"shirt_number":10,"position":3,"Favorite":false,"PicturePath":null},{"name":"Sarah MORTON","captain":false,"shirt_number":15,"position":0,"Favorite":false,"PicturePath":null},{"name":"Katie DUNCAN","captain":false,"shirt_number":16,"position":3,"Favorite":false,"PicturePath":null},{"name":"Hannah WILKINSON","captain":false,"shirt_number":17,"position":1,"Favorite":false,"PicturePath":null},{"name":"Steph SKILTON","captain":false,"shirt_number":18,"position":0,"Favorite":false,"PicturePath":null},{"name":"Paige SATCHELL","captain":false,"shirt_number":19,"position":1,"Favorite":false,"PicturePath":null},{"name":"Daisy CLEVERLEY","captain":false,"shirt_number":20,"position":3,"Favorite":false,"PicturePath":null},{"name":"Victoria ESSON","captain":false,"shirt_number":21,"position":2,"Favorite":false,"PicturePath":null},{"name":"Nadia OLLA","captain":false,"shirt_number":23,"position":2,"Favorite":false,"PicturePath":null},{"name":"Erin NAYLER","captain":false,"shirt_number":1,"position":2,"Favorite":true,"PicturePath":"C:\\Users\\jkustan\\Pictures\\_1430201.jpg"},{"name":"Claudia ENDLER","captain":true,"shirt_number":1,"position":2,"Favorite":false,"PicturePath":null},{"name":"Carla GUERRERO","captain":false,"shirt_number":3,"position":0,"Favorite":false,"PicturePath":null},{"name":"Maria URRUTIA","captain":false,"shirt_number":9,"position":1,"Favorite":false,"PicturePath":null},{"name":"Yanara AEDO","captain":false,"shirt_number":10,"position":3,"Favorite":false,"PicturePath":null},{"name":"Su Helen GALAZ","captain":false,"shirt_number":15,"position":0,"Favorite":false,"PicturePath":null},{"name":"Javiera TORO","captain":false,"shirt_number":17,"position":0,"Favorite":false,"PicturePath":null},{"name":"Camila SAEZ","captain":false,"shirt_number":18,"position":0,"Favorite":false,"PicturePath":null},{"name":"Daniela ZAMORA","captain":false,"shirt_number":20,"position":1,"Favorite":false,"PicturePath":null},{"name":"Rosario BALMACEDA","captain":false,"shirt_number":21,"position":3,"Favorite":false,"PicturePath":null},{"name":"Rocio SOTO","captain":false,"shirt_number":2,"position":0,"Favorite":false,"PicturePath":null},{"name":"Valentina DIAZ","captain":false,"shirt_number":5,"position":0,"Favorite":false,"PicturePath":null},{"name":"Claudia SOTO","captain":false,"shirt_number":6,"position":3,"Favorite":false,"PicturePath":null},{"name":"Maria Jose ROJAS","captain":false,"shirt_number":7,"position":1,"Favorite":false,"PicturePath":null},{"name":"Yessenia LOPEZ","captain":false,"shirt_number":11,"position":3,"Favorite":false,"PicturePath":null},{"name":"Natalia CAMPOS","captain":false,"shirt_number":12,"position":2,"Favorite":false,"PicturePath":null},{"name":"Javiera GREZ","captain":false,"shirt_number":13,"position":1,"Favorite":false,"PicturePath":null},{"name":"Daniela PARDO","captain":false,"shirt_number":14,"position":3,"Favorite":false,"PicturePath":null},{"name":"Fernanda PINILLA","captain":false,"shirt_number":16,"position":0,"Favorite":false,"PicturePath":null},{"name":"Yessenia HUENTEO","captain":false,"shirt_number":19,"position":1,"Favorite":false,"PicturePath":null},{"name":"Elisa DURAN","captain":false,"shirt_number":22,"position":3,"Favorite":false,"PicturePath":null},{"name":"Ryan TORRERO","captain":false,"shirt_number":23,"position":2,"Favorite":false,"PicturePath":null},{"name":"Francisca LARA","captain":false,"shirt_number":4,"position":0,"Favorite":true,"PicturePath":null},{"name":"Karen ARAYA","captain":false,"shirt_number":8,"position":3,"Favorite":true,"PicturePath":null},{"name":"Claudia ENDLER","captain":true,"shirt_number":1,"position":2,"Favorite":false,"PicturePath":null},{"name":"Carla GUERRERO","captain":false,"shirt_number":3,"position":0,"Favorite":false,"PicturePath":null},{"name":"Maria URRUTIA","captain":false,"shirt_number":9,"position":1,"Favorite":false,"PicturePath":null},{"name":"Yanara AEDO","captain":false,"shirt_number":10,"position":3,"Favorite":false,"PicturePath":null},{"name":"Su Helen GALAZ","captain":false,"shirt_number":15,"position":0,"Favorite":false,"PicturePath":null},{"name":"Javiera TORO","captain":false,"shirt_number":17,"position":0,"Favorite":false,"PicturePath":null},{"name":"Camila SAEZ","captain":false,"shirt_number":18,"position":0,"Favorite":false,"PicturePath":null},{"name":"Daniela ZAMORA","captain":false,"shirt_number":20,"position":1,"Favorite":false,"PicturePath":null},{"name":"Rosario BALMACEDA","captain":false,"shirt_number":21,"position":3,"Favorite":false,"PicturePath":null},{"name":"Rocio SOTO","captain":false,"shirt_number":2,"position":0,"Favorite":false,"PicturePath":null},{"name":"Valentina DIAZ","captain":false,"shirt_number":5,"position":0,"Favorite":false,"PicturePath":null},{"name":"Claudia SOTO","captain":false,"shirt_number":6,"position":3,"Favorite":false,"PicturePath":null},{"name":"Maria Jose ROJAS","captain":false,"shirt_number":7,"position":1,"Favorite":false,"PicturePath":null},{"name":"Yessenia LOPEZ","captain":false,"shirt_number":11,"position":3,"Favorite":false,"PicturePath":null},{"name":"Natalia CAMPOS","captain":false,"shirt_number":12,"position":2,"Favorite":false,"PicturePath":null},{"name":"Javiera GREZ","captain":false,"shirt_number":13,"position":1,"Favorite":false,"PicturePath":null},{"name":"Daniela PARDO","captain":false,"shirt_number":14,"position":3,"Favorite":false,"PicturePath":null},{"name":"Fernanda PINILLA","captain":false,"shirt_number":16,"position":0,"Favorite":false,"PicturePath":null},{"name":"Yessenia HUENTEO","captain":false,"shirt_number":19,"position":1,"Favorite":false,"PicturePath":null},{"name":"Elisa DURAN","captain":false,"shirt_number":22,"position":3,"Favorite":false,"PicturePath":null},{"name":"Ryan TORRERO","captain":false,"shirt_number":23,"position":2,"Favorite":false,"PicturePath":null},{"name":"Francisca LARA","captain":false,"shirt_number":4,"position":0,"Favorite":true,"PicturePath":null},{"name":"Karen ARAYA","captain":false,"shirt_number":8,"position":3,"Favorite":true,"PicturePath":null}]
